AUTHOR.txt
CHANGES.txt
README.txt
setup.py
src/cmf/__init__.py
src/cmf.pt.egg-info/PKG-INFO
src/cmf.pt.egg-info/SOURCES.txt
src/cmf.pt.egg-info/dependency_links.txt
src/cmf.pt.egg-info/entry_points.txt
src/cmf.pt.egg-info/namespace_packages.txt
src/cmf.pt.egg-info/not-zip-safe
src/cmf.pt.egg-info/requires.txt
src/cmf.pt.egg-info/top_level.txt
src/cmf/pt/__init__.py
src/cmf/pt/configure.zcml
src/cmf/pt/fs.py