Metadata-Version: 1.0
Name: cmf.pt
Version: 1.0
Summary: Bridge to use Chameleon with Zope 2 and CMF.
Home-page: UNKNOWN
Author: Malthe Borch and the Zope community
Author-email: zope-dev@zope.org
License: ZPL
Platform: UNKNOWN
Classifier: Framework :: Plone
Classifier: Framework :: Zope2
Classifier: Programming Language :: Python
Classifier: Topic :: Text Processing :: Markup :: HTML
Classifier: Topic :: Text Processing :: Markup :: XML
